   {"nodes":[{"name":"zero","group":1},{"name":"one","group":1},{"name":"two","group":1},{"name":"three","group":1},{"name":"four","group":1},{"name":"five","group":1},{"name":"six","group":1},{"name":"seven","group":1},{"name":"eight","group":1},{"name":"nine","group":1},{"name":"ten","group":1},{"name":"eleven","group":2},{"name":"twelve","group":2},{"name":"thirteen","group":3},{"name":"fourteen","group":2},{"name":"fifteen","group":2},{"name":"sixteen","group":2},{"name":"seventeen","group":3},{"name":"eighteen","group":3},{"name":"nineteen","group":3},{"name":"twenty","group":3},{"name":"twenty-one","group":3},{"name":"twenty-two","group":3},{"name":"twenty-three","group":3},{"name":"twenty-four","group":3},{"name":"twenty-five","group":4}],
                "links":[]}